data_repo_client/__init__.py
data_repo_client/api_client.py
data_repo_client/configuration.py
data_repo_client/exceptions.py
data_repo_client/rest.py
data_repo_client/api/__init__.py
data_repo_client/api/admin_api.py
data_repo_client/api/configs_api.py
data_repo_client/api/data_repository_service_api.py
data_repo_client/api/datasets_api.py
data_repo_client/api/duos_api.py
data_repo_client/api/jobs_api.py
data_repo_client/api/journal_api.py
data_repo_client/api/profiles_api.py
data_repo_client/api/register_api.py
data_repo_client/api/repository_api.py
data_repo_client/api/resources_api.py
data_repo_client/api/search_api.py
data_repo_client/api/snapshot_access_request_api.py
data_repo_client/api/snapshots_api.py
data_repo_client/api/unauthenticated_api.py
data_repo_client/api/upgrade_api.py
data_repo_client/models/__init__.py
data_repo_client/models/access_info_big_query_model.py
data_repo_client/models/access_info_big_query_model_table.py
data_repo_client/models/access_info_model.py
data_repo_client/models/access_info_parquet_model.py
data_repo_client/models/access_info_parquet_model_table.py
data_repo_client/models/add_auth_domain_response_model.py
data_repo_client/models/asset_model.py
data_repo_client/models/asset_table_model.py
data_repo_client/models/billing_profile_model.py
data_repo_client/models/billing_profile_request_model.py
data_repo_client/models/billing_profile_update_model.py
data_repo_client/models/bulk_load_array_request_model.py
data_repo_client/models/bulk_load_array_result_model.py
data_repo_client/models/bulk_load_file_model.py
data_repo_client/models/bulk_load_file_result_model.py
data_repo_client/models/bulk_load_file_state.py
data_repo_client/models/bulk_load_history_model.py
data_repo_client/models/bulk_load_history_model_list.py
data_repo_client/models/bulk_load_request_model.py
data_repo_client/models/bulk_load_result_model.py
data_repo_client/models/cloud_platform.py
data_repo_client/models/column_model.py
data_repo_client-2.364.0.dist-info/METADATA
data_repo_client-2.364.0.dist-info/WHEEL
data_repo_client-2.364.0.dist-info/top_level.txt
data_repo_client-2.364.0.dist-info/RECORD
