Metadata-Version: 2.1
Name: data-repo-client
Version: 2.364.0
Summary: Data Repository API
Home-page: 
Author: OpenAPI Generator community
Author-email: team@openapitools.org
License: Apache 2.0
Keywords: OpenAPI,OpenAPI-Generator,Data Repository API
Requires-Dist: urllib3 >=1.15
Requires-Dist: six >=1.10
Requires-Dist: certifi
Requires-Dist: python-dateutil
